WDL/CLI.py
WDL/Env.py
WDL/Error.py
WDL/Expr.py
WDL/Lint.py
WDL/StdLib.py
WDL/Tree.py
WDL/Type.py
WDL/Value.py
WDL/Walker.py
WDL/Zip.py
WDL/__init__.py
WDL/__main__.py
WDL/_grammar.py
WDL/_grammar_old.py
WDL/_parser.py
WDL/_util.py
WDL/_version.py
WDL/py.typed
WDL/runtime/__init__.py
WDL/runtime/_statusbar.py
WDL/runtime/cache.py
WDL/runtime/config.py
WDL/runtime/download.py
WDL/runtime/error.py
WDL/runtime/task.py
WDL/runtime/task_container.py
WDL/runtime/workflow.py
WDL/runtime/backend/__init__.py
WDL/runtime/backend/cli_subprocess.py
WDL/runtime/backend/docker_swarm.py
WDL/runtime/backend/podman.py
WDL/runtime/backend/singularity.py
WDL/runtime/backend/udocker.py
WDL/runtime/config_templates/default.cfg
miniwdl-1.13.1.dist-info/licenses/LICENSE
miniwdl-1.13.1.dist-info/METADATA
miniwdl-1.13.1.dist-info/WHEEL
miniwdl-1.13.1.dist-info/entry_points.txt
miniwdl-1.13.1.dist-info/top_level.txt
miniwdl-1.13.1.dist-info/RECORD
