Metadata-Version: 2.4
Name: miniwdl
Version: 1.13.1
Summary: Workflow Description Language (WDL) local runner & developer toolkit
Author-email: CZI <security@chanzuckerberg.com>
License: MIT
Project-URL: Homepage, https://github.com/chanzuckerberg/miniwdl
Classifier: Programming Language :: Python :: 3 :: Only
Classifier: License :: OSI Approved :: MIT License
Classifier: Operating System :: OS Independent
Classifier: Development Status :: 5 - Production/Stable
Classifier: Topic :: Scientific/Engineering :: Bio-Informatics
Classifier: Topic :: Software Development :: Interpreters
Requires-Python: >=3.8
License-File: LICENSE
Requires-Dist: importlib-metadata>=3.10.1
Requires-Dist: regex>=2020.4.4
Requires-Dist: xdg>=5.0.0
Requires-Dist: docker>=3.4.0
Requires-Dist: ruamel.yaml~=0.18
Requires-Dist: argcomplete<4,>=3
Requires-Dist: pygtail~=0.14
Requires-Dist: coloredlogs<16,>=15
Requires-Dist: python-json-logger<4,>=2
Requires-Dist: lark~=1.3
Requires-Dist: questionary<3,>=2
Requires-Dist: psutil<8,>=5
Provides-Extra: dev
Requires-Dist: ruff; extra == "dev"
Requires-Dist: mypy; extra == "dev"
Requires-Dist: pytest; extra == "dev"
Requires-Dist: testfixtures; extra == "dev"
Requires-Dist: pytest-xdist; extra == "dev"
Requires-Dist: pytest-cov; extra == "dev"
Requires-Dist: coverage; extra == "dev"
Requires-Dist: python-coveralls; extra == "dev"
Requires-Dist: build; extra == "dev"
Requires-Dist: wheel; extra == "dev"
Requires-Dist: twine; extra == "dev"
Requires-Dist: sphinx; extra == "dev"
Requires-Dist: sphinx-autobuild; extra == "dev"
Requires-Dist: sphinx_rtd_theme; extra == "dev"
Requires-Dist: sphinx-argparse; extra == "dev"
Requires-Dist: recommonmark; extra == "dev"
Requires-Dist: graphviz; extra == "dev"
Requires-Dist: boto3; extra == "dev"
Dynamic: license-file
